[
  {
    "rec_type": "NPC_",
    "record_id": "Player",
    "name": "Troll",
    "mesh": "",
    "race": "troll",
    "class_id": "troll_warrior",
    "faction": "",
    "head": "",
    "hair": "",
    "script": "",
    "npc_flags": 16,
    "npdt_autocalc": {
      "level": 1,
      "disposition": 50,
      "reputation": 0,
      "rank": 0,
      "gold": 0
    },
    "inventory": [],
    "spells": ["jtt_troll_regen"],
    "ai_data": {"hello": 0, "fight": 0, "flee": 0, "alarm": 0, "services": 0},
    "ai_packages": [],
    "transport": [],
    "flags": 0
  },
  {
    "rec_type": "NPC_",
    "record_id": "jtt_forest_warrior",
    "name": "Forest Troll Warrior",
    "mesh": "",
    "race": "troll",
    "class_id": "troll_warrior",
    "faction": "forest_trolls",
    "head": "",
    "hair": "",
    "script": "",
    "npc_flags": 16,
    "npdt_autocalc": {
      "level": 5,
      "disposition": 50,
      "reputation": 0,
      "rank": 0,
      "gold": 20
    },
    "inventory": [
      {"count": 1, "item_id": "jtt_bone_club"},
      {"count": 1, "item_id": "jtt_tribal_loincloth"},
      {"count": 2, "item_id": "jtt_jungle_berry"},
      {"count": 5, "item_id": "jtt_shell_token"}
    ],
    "spells": [],
    "ai_data": {
      "hello": 0,
      "fight": 0,
      "flee": 20,
      "alarm": 0,
      "services": 0
    },
    "ai_packages": [
      {"type": "AI_W", "raw_hex": "0001050000000000000000000100"}
    ],
    "transport": [],
    "flags": 0
  },
  {
    "rec_type": "NPC_",
    "record_id": "jtt_forest_shaman",
    "name": "Forest Troll Shaman",
    "mesh": "",
    "race": "troll",
    "class_id": "troll_shaman",
    "faction": "forest_trolls",
    "head": "",
    "hair": "",
    "script": "",
    "npc_flags": 16,
    "npdt_autocalc": {
      "level": 4,
      "disposition": 60,
      "reputation": 5,
      "rank": 1,
      "gold": 30
    },
    "inventory": [
      {"count": 1, "item_id": "jtt_vine_whip"},
      {"count": 1, "item_id": "jtt_shaman_robe"},
      {"count": 1, "item_id": "jtt_bone_necklace"},
      {"count": 2, "item_id": "jtt_voodoo_doll"},
      {"count": 1, "item_id": "jtt_jungle_lore"},
      {"count": 3, "item_id": "jtt_shell_token"}
    ],
    "spells": ["jtt_voodoo_hex", "jtt_shadow_step"],
    "ai_data": {
      "hello": 0,
      "fight": 0,
      "flee": 40,
      "alarm": 0,
      "services": 129
    },
    "ai_packages": [
      {"type": "AI_W", "raw_hex": "80000800000000000a0000000100"}
    ],
    "transport": [],
    "flags": 0
  },
  {
    "rec_type": "NPC_",
    "record_id": "jtt_river_fisherman",
    "name": "River Troll Fisherman",
    "mesh": "",
    "race": "troll",
    "class_id": "troll_hunter",
    "faction": "river_trolls",
    "head": "",
    "hair": "",
    "script": "",
    "npc_flags": 16,
    "npdt_autocalc": {
      "level": 3,
      "disposition": 70,
      "reputation": 0,
      "rank": 0,
      "gold": 50
    },
    "inventory": [
      {"count": 1, "item_id": "jtt_flint_dagger"},
      {"count": 1, "item_id": "jtt_tribal_loincloth"},
      {"count": 5, "item_id": "jtt_jungle_berry"},
      {"count": 10, "item_id": "jtt_shell_token"}
    ],
    "spells": [],
    "ai_data": {
      "hello": 0,
      "fight": 0,
      "flee": 40,
      "alarm": 0,
      "services": 1
    },
    "ai_packages": [
      {"type": "AI_W", "raw_hex": "00010800000000000a0000000100"}
    ],
    "transport": [],
    "flags": 0
  },
  {
    "rec_type": "NPC_",
    "record_id": "jtt_river_defender",
    "name": "River Troll Defender",
    "mesh": "",
    "race": "troll",
    "class_id": "troll_warrior",
    "faction": "river_trolls",
    "head": "",
    "hair": "",
    "script": "",
    "npc_flags": 16,
    "npdt_autocalc": {
      "level": 6,
      "disposition": 50,
      "reputation": 0,
      "rank": 1,
      "gold": 15
    },
    "inventory": [
      {"count": 1, "item_id": "jtt_stone_hatchet"},
      {"count": 1, "item_id": "jtt_bone_shield"},
      {"count": 1, "item_id": "jtt_hide_cuirass"},
      {"count": 1, "item_id": "jtt_tribal_loincloth"},
      {"count": 3, "item_id": "jtt_shell_token"}
    ],
    "spells": [],
    "ai_data": {
      "hello": 0,
      "fight": 0,
      "flee": 20,
      "alarm": 0,
      "services": 0
    },
    "ai_packages": [
      {"type": "AI_W", "raw_hex": "0001050000000000000000000100"}
    ],
    "transport": [],
    "flags": 0
  },
  {
    "rec_type": "NPC_",
    "record_id": "jtt_blood_berserker",
    "name": "Blood Troll Berserker",
    "mesh": "",
    "race": "troll",
    "class_id": "troll_berserker",
    "faction": "blood_trolls",
    "head": "",
    "hair": "",
    "script": "",
    "npc_flags": 16,
    "npdt_autocalc": {
      "level": 7,
      "disposition": 20,
      "reputation": 0,
      "rank": 1,
      "gold": 10
    },
    "inventory": [
      {"count": 1, "item_id": "jtt_war_maul"},
      {"count": 1, "item_id": "jtt_tribal_loincloth"},
      {"count": 1, "item_id": "jtt_berserker_blood"},
      {"count": 2, "item_id": "jtt_shell_token"}
    ],
    "spells": ["jtt_blood_frenzy"],
    "ai_data": {
      "hello": 0,
      "fight": 0,
      "flee": 5,
      "alarm": 0,
      "services": 0
    },
    "ai_packages": [
      {"type": "AI_W", "raw_hex": "0002030000000000000000000100"}
    ],
    "transport": [],
    "flags": 0
  },
  {
    "rec_type": "NPC_",
    "record_id": "jtt_shadow_hexer",
    "name": "Shadow Troll Hexer",
    "mesh": "",
    "race": "troll",
    "class_id": "troll_shaman",
    "faction": "shadow_trolls",
    "head": "",
    "hair": "",
    "script": "",
    "npc_flags": 16,
    "npdt_autocalc": {
      "level": 6,
      "disposition": 40,
      "reputation": 10,
      "rank": 2,
      "gold": 40
    },
    "inventory": [
      {"count": 1, "item_id": "jtt_vine_whip"},
      {"count": 1, "item_id": "jtt_shaman_robe"},
      {"count": 2, "item_id": "jtt_voodoo_doll"},
      {"count": 1, "item_id": "jtt_voodoo_potion"},
      {"count": 5, "item_id": "jtt_shell_token"}
    ],
    "spells": ["jtt_voodoo_hex", "jtt_shadow_step", "jtt_serpent_curse"],
    "ai_data": {
      "hello": 0,
      "fight": 0,
      "flee": 30,
      "alarm": 0,
      "services": 0
    },
    "ai_packages": [
      {"type": "AI_W", "raw_hex": "80000800000000000a0000000100"}
    ],
    "transport": [],
    "flags": 0
  },
  {
    "rec_type": "NPC_",
    "record_id": "jtt_tribal_elder",
    "name": "Tribal Elder",
    "mesh": "",
    "race": "troll",
    "class_id": "troll_shaman",
    "faction": "",
    "head": "",
    "hair": "",
    "script": "",
    "npc_flags": 16,
    "npdt_autocalc": {
      "level": 15,
      "disposition": 80,
      "reputation": 50,
      "rank": 0,
      "gold": 200
    },
    "inventory": [
      {"count": 1, "item_id": "jtt_obsidian_spear"},
      {"count": 1, "item_id": "jtt_bone_necklace"},
      {"count": 1, "item_id": "jtt_shaman_robe"},
      {"count": 1, "item_id": "jtt_troll_idol"},
      {"count": 1, "item_id": "jtt_jungle_lore"},
      {"count": 1, "item_id": "jtt_tribal_recipes"},
      {"count": 20, "item_id": "jtt_shell_token"}
    ],
    "spells": ["jtt_voodoo_hex", "jtt_shadow_step", "jtt_jungle_call", "jtt_troll_regen"],
    "ai_data": {
      "hello": 0,
      "fight": 0,
      "flee": 60,
      "alarm": 0,
      "services": 129
    },
    "ai_packages": [
      {"type": "AI_W", "raw_hex": "00001400000000000a0a0a000000"}
    ],
    "transport": [],
    "flags": 0
  },
  {
    "rec_type": "NPC_",
    "record_id": "jtt_player_troll",
    "name": "Player Troll",
    "mesh": "",
    "race": "troll",
    "class_id": "troll_warrior",
    "faction": "",
    "head": "",
    "hair": "",
    "script": "JTT_PlayerStart",
    "npc_flags": 16,
    "npdt_autocalc": {
      "level": 1,
      "disposition": 50,
      "reputation": 0,
      "rank": 0,
      "gold": 0
    },
    "inventory": [
      {"count": 1, "item_id": "jtt_bone_club"},
      {"count": 1, "item_id": "jtt_tribal_loincloth"},
      {"count": 3, "item_id": "jtt_jungle_berry"},
      {"count": 5, "item_id": "jtt_shell_token"}
    ],
    "spells": ["jtt_troll_regen"],
    "ai_data": {
      "hello": 0,
      "fight": 0,
      "flee": 30,
      "alarm": 0,
      "services": 0
    },
    "ai_packages": [],
    "transport": [],
    "flags": 0
  }
]
